{
    "id": 384,
    "name": "Easy - i LOVE Camellia",
    "author": "username999",
    "creators": ["username999"],
    "verifier": "LTTFrance",
    "verification": "https://youtu.be/FA0vV-G2f2E",
    "percentToQualify": "100",
    "password": "Free To Copy",
    "records": [
        {
            "user": "LordRetrace",
            "link": "https://www.youtube.com/watch?v=hDkvEF2dxWw",
            "percent": 100,
            "hz": 240
        },
        {
            "user": "LicorneGDPS",
            "link": "https://www.youtube.com/watch?v=qt1_lpSGQbU",
            "percent": 100,
            "hz": 120
        }
    ]
}
